{"pages":[{"page":"艾丽(东方Project)","url":"/艾丽(东方Project)"},{"page":"爱丽丝(东方Project旧作)","url":"/爱丽丝(东方Project旧作)"},{"page":"爱莲(东方Project)","url":"/爱莲(东方Project)"},{"page":"奥莲姬","url":"/奥莲姬"},{"page":"北白河千百合","url":"/北白河千百合"},{"page":"博丽灵梦(东方Project旧作)","url":"/博丽灵梦(东方Project旧作)"},{"page":"冈崎梦美","url":"/冈崎梦美"},{"page":"轮妖精","url":"/轮妖精"},{"page":"光子(东方怪绮谈)","url":"/光子(东方怪绮谈)"},{"page":"光子(东方幻想乡)","url":"/光子(东方幻想乡)"},{"page":"胡桃(东方Project)","url":"/胡桃(东方Project)"},{"page":"幻梦盘","url":"/幻梦盘"},{"page":"幻想乡EX面中","url":"/幻想乡EX面中"},{"page":"幻月","url":"/幻月"},{"page":"矜羯罗","url":"/矜羯罗"},{"page":"菊理(东方Project)","url":"/菊理(东方Project)"},{"page":"卡娜·安娜贝拉尔","url":"/卡娜·安娜贝拉尔"},{"page":"里香","url":"/里香"},{"page":"露西亚(东方Project)","url":"/露西亚(东方Project)"},{"page":"露易兹(东方Project)","url":"/露易兹(东方Project)"},{"page":"玛O奇","url":"/玛O奇"},{"page":"魅魔(东方Project)","url":"/魅魔(东方Project)"},{"page":"梦月","url":"/梦月"},{"page":"梦子","url":"/梦子"},{"page":"咪咪号","url":"/咪咪号"},{"page":"明罗","url":"/明罗"},{"page":"魔界人(东方怪绮谈)","url":"/魔界人(东方怪绮谈)"},{"page":"魔镜(东方Project)","url":"/魔镜(东方Project)"},{"page":"魔天使","url":"/魔天使"},{"page":"炮台(东方Project)","url":"/炮台(东方Project)"},{"page":"萨丽爱尔","url":"/萨丽爱尔"},{"page":"萨拉(东方Project)","url":"/萨拉(东方Project)"},{"page":"山步","url":"/山步"},{"page":"神镜","url":"/神镜"},{"page":"神绮","url":"/神绮"},{"page":"神玉","url":"/神玉"},{"page":"苏格拉底(东方Project)","url":"/苏格拉底(东方Project)"},{"page":"王牌(东方Project)","url":"/王牌(东方Project)"},{"page":"舞(东方Project)","url":"/舞(东方Project)"},{"page":"雾雨魔理沙(东方Project旧作)","url":"/雾雨魔理沙(东方Project旧作)"},{"page":"小精灵(东方Project)","url":"/小精灵(东方Project)"},{"page":"小兔姬","url":"/小兔姬"},{"page":"玄爷","url":"/玄爷"},{"page":"雪(东方Project)","url":"/雪(东方Project)"},{"page":"妖精(东方怪绮谈)","url":"/妖精(东方怪绮谈)"},{"page":"妖莲花","url":"/妖莲花"},{"page":"妖奈","url":"/妖奈"},{"page":"依莉斯(东方Project)","url":"/依莉斯(东方Project)"},{"page":"幽香","url":"/幽香"},{"page":"幽玄魔眼","url":"/幽玄魔眼"},{"page":"战车(东方Project)","url":"/战车(东方Project)"},{"page":"朝仓理香子","url":"/朝仓理香子"},{"page":"诅咒子","url":"/诅咒子"}],"subcategories":[]}