{"pages":[{"url":"/Template:Toaru_top","name":"Template:Toaru top"},{"url":"/爱华斯","name":"爱华斯"},{"url":"/奥索拉·阿奎纳","name":"奥索拉·阿奎纳"},{"url":"/白井黑子","name":"白井黑子"},{"url":"/薄绢休味","name":"薄绢休味"},{"url":"/布束砥信","name":"布束砥信"},{"url":"/操齿凉子","name":"操齿凉子"},{"url":"/查乐","name":"查乐"},{"url":"/长点上机学园","name":"长点上机学园"},{"url":"/超电磁炮","name":"超电磁炮"},{"url":"/初春饰利","name":"初春饰利"},{"url":"/吹寄制理","name":"吹寄制理"},{"url":"/春上衿衣","name":"春上衿衣"},{"url":"/大姐头(某科学的超电磁炮)","name":"大姐头(某科学的超电磁炮)"},{"url":"/第七学区立栅川中学校","name":"第七学区立栅川中学校"},{"url":"/电脑配件","name":"电脑配件"},{"url":"/多莉(某科学的超电磁炮)","name":"多莉(某科学的超电磁炮)"},{"url":"/鳄河雷斧","name":"鳄河雷斧"},{"url":"/帆风润子","name":"帆风润子"},{"url":"/番外个体","name":"番外个体"},{"url":"/芳川桔梗","name":"芳川桔梗"},{"url":"/菲布莉","name":"菲布莉"},{"url":"/风斩冰华","name":"风斩冰华"},{"url":"/芙兰达·塞维伦","name":"芙兰达·塞维伦"},{"url":"/弓箭猎虎","name":"弓箭猎虎"},{"url":"/弓箭入鹿","name":"弓箭入鹿"},{"url":"/固法美伟","name":"固法美伟"},{"url":"/黑妻绵流","name":"黑妻绵流"},{"url":"/幻想御手","name":"幻想御手"},{"url":"/黄泉川爱穗","name":"黄泉川爱穗"},{"url":"/婚后光子","name":"婚后光子"},{"url":"/姬神秋沙","name":"姬神秋沙"},{"url":"/结标淡希","name":"结标淡希"},{"url":"/警备员(魔法禁书目录)","name":"警备员(魔法禁书目录)"},{"url":"/警策看取","name":"警策看取"},{"url":"/绢旗最爱","name":"绢旗最爱"},{"url":"/口囃子早鸟","name":"口囃子早鸟"},{"url":"/LV5","name":"LV5"},{"url":"/蓝发耳环","name":"蓝发耳环"},{"url":"/铃科百合子","name":"铃科百合子"},{"url":"/柳迫碧美","name":"柳迫碧美"},{"url":"/泷壶理后","name":"泷壶理后"},{"url":"/龙神乙姬","name":"龙神乙姬"},{"url":"/萝拉·斯图亚特","name":"萝拉·斯图亚特"},{"url":"/马场芳郎","name":"马场芳郎"},{"url":"/麦野沉利","name":"麦野沉利"},{"url":"/美山写影","name":"美山写影"},{"url":"/明美(某科学的超电磁炮)","name":"明美(某科学的超电磁炮)"},{"url":"/冥土追魂","name":"冥土追魂"},{"url":"/某科学的超电磁炮","name":"某科学的超电磁炮"},{"url":"/木山春生","name":"木山春生"},{"url":"/木原病理","name":"木原病理"},{"url":"/木原那由他","name":"木原那由他"},{"url":"/木原脑干","name":"木原脑干"},{"url":"/木原圆周","name":"木原圆周"},{"url":"/泡浮万彬","name":"泡浮万彬"},{"url":"/前方之风","name":"前方之风"},{"url":"/切斑芽美","name":"切斑芽美"},{"url":"/亲船素甘","name":"亲船素甘"},{"url":"/青星铃兰","name":"青星铃兰"},{"url":"/上条当麻","name":"上条当麻"},{"url":"/上条诗菜","name":"上条诗菜"},{"url":"/舍监(魔法禁书目录)","name":"舍监(魔法禁书目录)"},{"url":"/神裂火织","name":"神裂火织"},{"url":"/食蜂操祈","name":"食蜂操祈"},{"url":"/矢量操作","name":"矢量操作"},{"url":"/索绮特","name":"索绮特"},{"url":"/泰瑞丝缇娜·木原·莱夫雷恩","name":"泰瑞丝缇娜·木原·莱夫雷恩"},{"url":"/铁装缀里","name":"铁装缀里"},{"url":"/土御门舞夏","name":"土御门舞夏"},{"url":"/托尔(魔法禁书目录)","name":"托尔(魔法禁书目录)"},{"url":"/湾内绢保","name":"湾内绢保"},{"url":"/武藏野牛奶","name":"武藏野牛奶"},{"url":"/五和","name":"五和"},{"url":"/雾丘女学院","name":"雾丘女学院"},{"url":"/相园美央","name":"相园美央"},{"url":"/咲莲诱璃","name":"咲莲诱璃"},{"url":"/小睦","name":"小睦"},{"url":"/小佐古俊一","name":"小佐古俊一"},{"url":"/心理掌握","name":"心理掌握"},{"url":"/削板军霸","name":"削板军霸"},{"url":"/雪莉·克伦威尔","name":"雪莉·克伦威尔"},{"url":"/学园都市","name":"学园都市"},{"url":"/炎乘香炭","name":"炎乘香炭"},{"url":"/一方通行","name":"一方通行"},{"url":"/茵蒂克丝","name":"茵蒂克丝"},{"url":"/樱坂风雅","name":"樱坂风雅"},{"url":"/有富春树","name":"有富春树"},{"url":"/御坂10031号","name":"御坂10031号"},{"url":"/御坂10032","name":"御坂10032"},{"url":"/御坂10777号","name":"御坂10777号"},{"url":"/御坂19090号","name":"御坂19090号"},{"url":"/御坂9982号","name":"御坂9982号"},{"url":"/御坂美铃","name":"御坂美铃"},{"url":"/御坂妹妹","name":"御坂妹妹"},{"url":"/御坂美琴","name":"御坂美琴"},{"url":"/御坂网络","name":"御坂网络"},{"url":"/硲舍佳茄","name":"硲舍佳茄"},{"url":"/誉望万化","name":"誉望万化"},{"url":"/原谷矢文","name":"原谷矢文"},{"url":"/月咏小萌","name":"月咏小萌"},{"url":"/云川鞠亚","name":"云川鞠亚"},{"url":"/云川芹亚","name":"云川芹亚"},{"url":"/枝先绊理","name":"枝先绊理"},{"url":"/重福省帆","name":"重福省帆"},{"url":"/柊元响季","name":"柊元响季"},{"url":"/最后之作","name":"最后之作"},{"url":"/佐天泪子","name":"佐天泪子"},{"url":"/Template:孤独摇滚top","name":"Template:孤独摇滚top"},{"url":"/孤独摇滚！","name":"孤独摇滚！"},{"url":"/Template:孤独摇滚！","name":"Template:孤独摇滚！"},{"url":"/大槻悠悠子","name":"大槻悠悠子"},{"url":"/广井菊里","name":"广井菊里"},{"url":"/后藤二里","name":"后藤二里"},{"url":"/后藤一里","name":"后藤一里"},{"url":"/后藤直树","name":"后藤直树"},{"url":"/结束乐队","name":"结束乐队"},{"url":"/结束乐队LIVE-恒星-","name":"结束乐队LIVE-恒星-"},{"url":"/STARRY","name":"STARRY"},{"url":"/山田凉","name":"山田凉"},{"url":"/喜多郁代","name":"喜多郁代"},{"url":"/新宿FOLT","name":"新宿FOLT"},{"url":"/伊地知虹夏","name":"伊地知虹夏"},{"url":"/伊地知星歌","name":"伊地知星歌"},{"url":"/音响师","name":"音响师"},{"url":"/Template:EVATOP","name":"Template:EVATOP"},{"url":"/A.T.Field","name":"A.T.Field"},{"url":"/不能逃避、不能逃避、不能逃避","name":"不能逃避、不能逃避、不能逃避"},{"url":"/赤木律子","name":"赤木律子"},{"url":"/第三新东京市","name":"第三新东京市"},{"url":"/第三新东京市第一中学校","name":"第三新东京市第一中学校"},{"url":"/碇唯","name":"碇唯"},{"url":"/碇源堂","name":"碇源堂"},{"url":"/碇真嗣","name":"碇真嗣"},{"url":"/洞木光","name":"洞木光"},{"url":"/GEHIRN","name":"GEHIRN"},{"url":"/葛城美里","name":"葛城美里"},{"url":"/LCL","name":"LCL"},{"url":"/雷天使","name":"雷天使"},{"url":"/绫波丽","name":"绫波丽"},{"url":"/铃原樱","name":"铃原樱"},{"url":"/N2炸弹","name":"N2炸弹"},{"url":"/NERV","name":"NERV"},{"url":"/RE-TAKE","name":"RE-TAKE"},{"url":"/人类补完计划","name":"人类补完计划"},{"url":"/SEELE","name":"SEELE"},{"url":"/WILLE","name":"WILLE"},{"url":"/新·日本英雄宇宙之间的彩蛋以及联动","name":"新·日本英雄宇宙之间的彩蛋以及联动"},{"url":"/新世纪福音战士","name":"新世纪福音战士"},{"url":"/伊吹摩耶","name":"伊吹摩耶"},{"url":"/真希波·玛丽·伊兰崔亚斯","name":"真希波·玛丽·伊兰崔亚斯"},{"url":"/渚薰","name":"渚薰"},{"url":"/惣流·明日香·兰格雷","name":"惣流·明日香·兰格雷"},{"url":"/User:Tnt233/Sandbox","name":"User:Tnt233/Sandbox"},{"url":"/Template:少女终末旅行top","name":"Template:少女终末旅行top"},{"url":"/第6主塔人工智能","name":"第6主塔人工智能"},{"url":"/金泽","name":"金泽"},{"url":"/Nuko","name":"Nuko"},{"url":"/千户","name":"千户"},{"url":"/少女终末旅行","name":"少女终末旅行"},{"url":"/石井(少女终末旅行)","name":"石井(少女终末旅行)"},{"url":"/尤莉(少女终末旅行)","name":"尤莉(少女终末旅行)"},{"url":"/凉宫春日系列","name":"凉宫春日系列"},{"url":"/阿虚","name":"阿虚"},{"url":"/长门有希","name":"长门有希"},{"url":"/电研部部长","name":"电研部部长"},{"url":"/渡桥泰水","name":"渡桥泰水"},{"url":"/ENOZ","name":"ENOZ"},{"url":"/谷口","name":"谷口"},{"url":"/古泉一树","name":"古泉一树"},{"url":"/鹤屋","name":"鹤屋"},{"url":"/吉村美代子","name":"吉村美代子"},{"url":"/橘京子","name":"橘京子"},{"url":"/凉宫春日","name":"凉宫春日"},{"url":"/凉宫春日的消失","name":"凉宫春日的消失"},{"url":"/凉宫春日的忧郁","name":"凉宫春日的忧郁"},{"url":"/凉宫春日的追忆","name":"凉宫春日的追忆"},{"url":"/凉宫春日问题","name":"凉宫春日问题"},{"url":"/漫无止境的八月","name":"漫无止境的八月"},{"url":"/Nyoron_小鹤屋学姐","name":"Nyoron 小鹤屋学姐"},{"url":"/SOS团","name":"SOS团"},{"url":"/三味线(宠物)","name":"三味线(宠物)"},{"url":"/森园生","name":"森园生"},{"url":"/射手座之日","name":"射手座之日"},{"url":"/T(凉宫春日系列)","name":"T(凉宫春日系列)"},{"url":"/喜绿江美里","name":"喜绿江美里"},{"url":"/县立北高校","name":"县立北高校"},{"url":"/小长门有希的消失","name":"小长门有希的消失"},{"url":"/小凉宫春日的忧郁","name":"小凉宫春日的忧郁"},{"url":"/新川","name":"新川"},{"url":"/虚妹","name":"虚妹"},{"url":"/虚子","name":"虚子"},{"url":"/在虚构的故事当中寻求真实感的人脑袋一定有问题","name":"在虚构的故事当中寻求真实感的人脑袋一定有问题"},{"url":"/朝仓凉子(凉宫春日系列)","name":"朝仓凉子(凉宫春日系列)"},{"url":"/朝比奈实玖瑠","name":"朝比奈实玖瑠"},{"url":"/朝比奈实玖瑠的冒险","name":"朝比奈实玖瑠的冒险"},{"url":"/周防九曜","name":"周防九曜"},{"url":"/佐佐木(凉宫春日系列)","name":"佐佐木(凉宫春日系列)"},{"url":"/Template:轻音少女","name":"Template:轻音少女"},{"url":"/Template:轻音少女top","name":"Template:轻音少女top"},{"url":"/奥田直","name":"奥田直"},{"url":"/曾我部惠","name":"曾我部惠"},{"url":"/冲山阳二","name":"冲山阳二"},{"url":"/DEATH_DEVIL","name":"DEATH DEVIL"},{"url":"/放学后TEA_TIME","name":"放学后TEA TIME"},{"url":"/河口纪美","name":"河口纪美"},{"url":"/和田晶","name":"和田晶"},{"url":"/吉田菖","name":"吉田菖"},{"url":"/卷上君子","name":"卷上君子"},{"url":"/堀込老师","name":"堀込老师"},{"url":"/立花姬子","name":"立花姬子"},{"url":"/林幸","name":"林幸"},{"url":"/铃木纯","name":"铃木纯"},{"url":"/木下静香","name":"木下静香"},{"url":"/平泽唯","name":"平泽唯"},{"url":"/平泽忧","name":"平泽忧"},{"url":"/齐藤堇","name":"齐藤堇"},{"url":"/琴吹䌷","name":"琴吹䌷"},{"url":"/清水响子","name":"清水响子"},{"url":"/轻音少女","name":"轻音少女"},{"url":"/轻音少女/路人角色列表","name":"轻音少女/路人角色列表"},{"url":"/Template:轻音少女3年2班","name":"Template:轻音少女3年2班"},{"url":"/秋山澪","name":"秋山澪"},{"url":"/若王子一恋","name":"若王子一恋"},{"url":"/若叶Girls","name":"若叶Girls"},{"url":"/山中佐和子","name":"山中佐和子"},{"url":"/十万元之手","name":"十万元之手"},{"url":"/树H","name":"树H"},{"url":"/松本美冬","name":"松本美冬"},{"url":"/田井中聪","name":"田井中聪"},{"url":"/田井中律","name":"田井中律"},{"url":"/小猪(轻音少女)","name":"小猪(轻音少女)"},{"url":"/野岛千佳","name":"野岛千佳"},{"url":"/樱丘女子高等学校","name":"樱丘女子高等学校"},{"url":"/真锅和","name":"真锅和"},{"url":"/中野梓","name":"中野梓"},{"url":"/梓喵2号","name":"梓喵2号"},{"url":"/八坂红","name":"八坂红"},{"url":"/白石稔(幸运星)","name":"白石稔(幸运星)"},{"url":"/成实唯","name":"成实唯"},{"url":"/毒岛未来","name":"毒岛未来"},{"url":"/峰岸绫乃","name":"峰岸绫乃"},{"url":"/高良美幸","name":"高良美幸"},{"url":"/高良由香里","name":"高良由香里"},{"url":"/宫河家的空腹","name":"宫河家的空腹"},{"url":"/宫河日向","name":"宫河日向"},{"url":"/宫河日影","name":"宫河日影"},{"url":"/黑井奈那子","name":"黑井奈那子"},{"url":"/陵樱学园高等学校","name":"陵樱学园高等学校"},{"url":"/帕特莉西亚·马汀","name":"帕特莉西亚·马汀"},{"url":"/娶妻当如樱庭葵，生女当如泉此方","name":"娶妻当如樱庭葵，生女当如泉此方"},{"url":"/泉彼方","name":"泉彼方"},{"url":"/泉此方","name":"泉此方"},{"url":"/泉宗次郎","name":"泉宗次郎"},{"url":"/日下部美纱绪","name":"日下部美纱绪"},{"url":"/若濑泉","name":"若濑泉"},{"url":"/山边环","name":"山边环"},{"url":"/田村日和","name":"田村日和"},{"url":"/天原冬纪","name":"天原冬纪"},{"url":"/小神晶","name":"小神晶"},{"url":"/小早川优","name":"小早川优"},{"url":"/幸运星","name":"幸运星"},{"url":"/幸运星家教班_化学_轻轻松松融会贯通","name":"幸运星家教班 化学 轻轻松松融会贯通"},{"url":"/Template:幸运星top","name":"Template:幸运星top"},{"url":"/岩崎南","name":"岩崎南"},{"url":"/樱庭光","name":"樱庭光"},{"url":"/永森大和","name":"永森大和"},{"url":"/柊祭","name":"柊祭"},{"url":"/柊镜","name":"柊镜"},{"url":"/柊美纪","name":"柊美纪"},{"url":"/柊祈","name":"柊祈"},{"url":"/柊司","name":"柊司"},{"url":"/丹生谷森夏","name":"丹生谷森夏"},{"url":"/富㭴梦叶","name":"富㭴梦叶"},{"url":"/富㭴勇太","name":"富㭴勇太"},{"url":"/富㭴樟叶","name":"富㭴樟叶"},{"url":"/黑炎龙","name":"黑炎龙"},{"url":"/极东魔术昼寝结社之夏","name":"极东魔术昼寝结社之夏"},{"url":"/九十九七濑","name":"九十九七濑"},{"url":"/眠睡","name":"眠睡"},{"url":"/七宫智音","name":"七宫智音"},{"url":"/天虹旱","name":"天虹旱"},{"url":"/凸守早苗","name":"凸守早苗"},{"url":"/巫部风铃","name":"巫部风铃"},{"url":"/五月七日茴香","name":"五月七日茴香"},{"url":"/小鸟游六花","name":"小鸟游六花"},{"url":"/小鸟游十花","name":"小鸟游十花"},{"url":"/邪王真眼","name":"邪王真眼"},{"url":"/一场春梦","name":"一场春梦"},{"url":"/一色诚","name":"一色诚"},{"url":"/勇太的母亲","name":"勇太的母亲"},{"url":"/中二病也要谈恋爱！","name":"中二病也要谈恋爱！"},{"url":"/Template:中二病也要谈恋爱top","name":"Template:中二病也要谈恋爱top"},{"url":"/转手指","name":"转手指"},{"url":"/子子子子","name":"子子子子"},{"url":"/爱丽丝·玛格特罗依德","name":"爱丽丝·玛格特罗依德"},{"url":"/爱塔妮缇拉尔瓦","name":"爱塔妮缇拉尔瓦"},{"url":"/奥野田美宵","name":"奥野田美宵"},{"url":"/八坂神奈子","name":"八坂神奈子"},{"url":"/八意永琳","name":"八意永琳"},{"url":"/八云蓝","name":"八云蓝"},{"url":"/八云紫","name":"八云紫"},{"url":"/稗田阿求","name":"稗田阿求"},{"url":"/坂田合欢","name":"坂田合欢"},{"url":"/本居小铃","name":"本居小铃"},{"url":"/比那名居天子","name":"比那名居天子"},{"url":"/博丽灵梦","name":"博丽灵梦"},{"url":"/橙","name":"橙"},{"url":"/赤蛮奇","name":"赤蛮奇"},{"url":"/纯狐","name":"纯狐"},{"url":"/茨木华扇","name":"茨木华扇"},{"url":"/村纱水蜜","name":"村纱水蜜"},{"url":"/大鹫灵","name":"大鹫灵"},{"url":"/大鲶鱼","name":"大鲶鱼"},{"url":"/大妖精","name":"大妖精"},{"url":"/丁礼田舞","name":"丁礼田舞"},{"url":"/东风谷早苗","name":"东风谷早苗"},{"url":"/多多良小伞","name":"多多良小伞"},{"url":"/哆来咪·苏伊特","name":"哆来咪·苏伊特"},{"url":"/二岩猯藏","name":"二岩猯藏"},{"url":"/尔子田里乃","name":"尔子田里乃"},{"url":"/饭纲丸龙","name":"饭纲丸龙"},{"url":"/非想天则","name":"非想天则"},{"url":"/丰聪耳神子","name":"丰聪耳神子"},{"url":"/风见幽香","name":"风见幽香"},{"url":"/封兽鵺","name":"封兽鵺"},{"url":"/芙兰朵露·斯卡蕾特","name":"芙兰朵露·斯卡蕾特"},{"url":"/高丽野阿吽","name":"高丽野阿吽"},{"url":"/宫出口瑞灵","name":"宫出口瑞灵"},{"url":"/宫古芳香","name":"宫古芳香"},{"url":"/古明地觉","name":"古明地觉"},{"url":"/古明地恋","name":"古明地恋"},{"url":"/鬼人正邪","name":"鬼人正邪"},{"url":"/豪德寺三花","name":"豪德寺三花"},{"url":"/河城荷取","name":"河城荷取"},{"url":"/赫卡提亚·拉碧斯拉祖利","name":"赫卡提亚·拉碧斯拉祖利"},{"url":"/黑谷山女","name":"黑谷山女"},{"url":"/红美铃","name":"红美铃"},{"url":"/魂魄妖忌","name":"魂魄妖忌"},{"url":"/魂魄妖梦","name":"魂魄妖梦"},{"url":"/霍青娥","name":"霍青娥"},{"url":"/火焰猫燐","name":"火焰猫燐"},{"url":"/姬虫百百世","name":"姬虫百百世"},{"url":"/吉吊八千慧","name":"吉吊八千慧"},{"url":"/姬海棠果","name":"姬海棠果"},{"url":"/菅牧典","name":"菅牧典"},{"url":"/键山雏","name":"键山雏"},{"url":"/今泉影狼","name":"今泉影狼"},{"url":"/九十九八桥","name":"九十九八桥"},{"url":"/九十九弁弁","name":"九十九弁弁"},{"url":"/驹草山如","name":"驹草山如"},{"url":"/克劳恩皮丝","name":"克劳恩皮丝"},{"url":"/堀川雷鼓","name":"堀川雷鼓"},{"url":"/蕾蒂·霍瓦特洛克","name":"蕾蒂·霍瓦特洛克"},{"url":"/蕾拉·普莉兹姆利巴","name":"蕾拉·普莉兹姆利巴"},{"url":"/蕾米莉亚·斯卡蕾特","name":"蕾米莉亚·斯卡蕾特"},{"url":"/莉格露·奈特巴格","name":"莉格露·奈特巴格"},{"url":"/骊驹早鬼","name":"骊驹早鬼"},{"url":"/莉莉霍瓦特","name":"莉莉霍瓦特"},{"url":"/莉莉卡·普莉兹姆利巴","name":"莉莉卡·普莉兹姆利巴"},{"url":"/铃瑚","name":"铃瑚"},{"url":"/灵乌路空","name":"灵乌路空"},{"url":"/铃仙·优昙华院·因幡","name":"铃仙·优昙华院·因幡"},{"url":"/露米娅","name":"露米娅"},{"url":"/露娜切露德","name":"露娜切露德"},{"url":"/露娜萨·普莉兹姆利巴","name":"露娜萨·普莉兹姆利巴"},{"url":"/玛艾露贝莉·赫恩","name":"玛艾露贝莉·赫恩"},{"url":"/梅蒂欣·梅兰可莉","name":"梅蒂欣·梅兰可莉"},{"url":"/梅露兰·普莉兹姆利巴","name":"梅露兰·普莉兹姆利巴"},{"url":"/米斯蒂娅·萝蕾拉","name":"米斯蒂娅·萝蕾拉"},{"url":"/命莲","name":"命莲"},{"url":"/摩多罗隐岐奈","name":"摩多罗隐岐奈"},{"url":"/娜兹玲","name":"娜兹玲"},{"url":"/牛崎润美","name":"牛崎润美"},{"url":"/帕秋莉·诺蕾姬","name":"帕秋莉·诺蕾姬"},{"url":"/蓬莱山辉夜","name":"蓬莱山辉夜"},{"url":"/琪露诺","name":"琪露诺"},{"url":"/琪斯美","name":"琪斯美"},{"url":"/秦心","name":"秦心"},{"url":"/清兰","name":"清兰"},{"url":"/秋静叶","name":"秋静叶"},{"url":"/秋穰子","name":"秋穰子"},{"url":"/犬走椛","name":"犬走椛"},{"url":"/戎璎花","name":"戎璎花"},{"url":"/若鹭姬","name":"若鹭姬"},{"url":"/桑尼米尔克","name":"桑尼米尔克"},{"url":"/山城高岭","name":"山城高岭"},{"url":"/上白泽慧音","name":"上白泽慧音"},{"url":"/少名针妙丸","name":"少名针妙丸"},{"url":"/射命丸文","name":"射命丸文"},{"url":"/圣白莲","name":"圣白莲"},{"url":"/十六夜咲夜","name":"十六夜咲夜"},{"url":"/矢田寺成美","name":"矢田寺成美"},{"url":"/水桥帕露西","name":"水桥帕露西"},{"url":"/水獭灵","name":"水獭灵"},{"url":"/四季映姬·夜摩仙那度","name":"四季映姬·夜摩仙那度"},{"url":"/斯塔萨菲雅","name":"斯塔萨菲雅"},{"url":"/苏我屠自古","name":"苏我屠自古"},{"url":"/饕餮尤魔","name":"饕餮尤魔"},{"url":"/藤原妹红","name":"藤原妹红"},{"url":"/天弓千亦","name":"天弓千亦"},{"url":"/庭渡久侘歌","name":"庭渡久侘歌"},{"url":"/物部布都","name":"物部布都"},{"url":"/雾雨魔理沙","name":"雾雨魔理沙"},{"url":"/稀神探女","name":"稀神探女"},{"url":"/西行寺幽幽子","name":"西行寺幽幽子"},{"url":"/小野冢小町","name":"小野冢小町"},{"url":"/洩矢诹访子","name":"洩矢诹访子"},{"url":"/星熊勇仪","name":"星熊勇仪"},{"url":"/野狼灵","name":"野狼灵"},{"url":"/伊吹萃香","name":"伊吹萃香"},{"url":"/依神女苑","name":"依神女苑"},{"url":"/依神紫苑","name":"依神紫苑"},{"url":"/因幡帝","name":"因幡帝"},{"url":"/寅丸星","name":"寅丸星"},{"url":"/永江衣玖","name":"永江衣玖"},{"url":"/幽谷响子","name":"幽谷响子"},{"url":"/玉造魅须丸","name":"玉造魅须丸"},{"url":"/宇佐见堇子","name":"宇佐见堇子"},{"url":"/宇佐见莲子","name":"宇佐见莲子"},{"url":"/云居一轮","name":"云居一轮"},{"url":"/云山","name":"云山"},{"url":"/杖刀偶磨弓","name":"杖刀偶磨弓"},{"url":"/埴安神袿姬","name":"埴安神袿姬"},{"url":"/北白川雏子","name":"北白川雏子"},{"url":"/北白川豆大","name":"北白川豆大"},{"url":"/北白川福","name":"北白川福"},{"url":"/北白川馅子","name":"北白川馅子"},{"url":"/北白川玉子","name":"北白川玉子"},{"url":"/常盘绿","name":"常盘绿"},{"url":"/大路饼藏","name":"大路饼藏"},{"url":"/大路道子","name":"大路道子"},{"url":"/大路吾平","name":"大路吾平"},{"url":"/德拉·达高南池","name":"德拉·达高南池"},{"url":"/梅查·达高南池","name":"梅查·达高南池"},{"url":"/牧野神奈","name":"牧野神奈"},{"url":"/乔伊·达高南池","name":"乔伊·达高南池"},{"url":"/桃子(玉子市场)","name":"桃子(玉子市场)"},{"url":"/柚季","name":"柚季"},{"url":"/玉子市场","name":"玉子市场"},{"url":"/Template:玉子市场top","name":"Template:玉子市场top"},{"url":"/朝雾史织","name":"朝雾史织"}],"subcategories":[{"name":"某科学的超电磁炮音乐","url":"/Category:某科学的超电磁炮音乐","pages":[{"url":"/不用眼泪的Girls_Beat","name":"不用眼泪的Girls Beat"},{"url":"/超电磁少女Days","name":"超电磁少女Days"},{"url":"/初色Bloomy","name":"初色Bloomy"},{"url":"/待在这里","name":"待在这里"},{"url":"/Dear_My_Friend_-朝向未知的未来-","name":"Dear My Friend -朝向未知的未来-"},{"url":"/Dual_existence","name":"Dual existence"},{"url":"/Eternal_reality","name":"Eternal reality"},{"url":"/Final_phase","name":"Final phase"},{"url":"/Future_gazer","name":"Future gazer"},{"url":"/Grow_Slowly","name":"Grow Slowly"},{"url":"/Infinia","name":"Infinia"},{"url":"/LEVEL5_-judgelight-","name":"LEVEL5 -judgelight-"},{"url":"/Links","name":"Links"},{"url":"/某科学的超乐曲集","name":"某科学的超乐曲集"},{"url":"/Nameless_story(某科学的超电磁炮)","name":"Nameless story(某科学的超电磁炮)"},{"url":"/Only_my_railgun","name":"Only my railgun"},{"url":"/Real_Force","name":"Real Force"},{"url":"/SMILE_-You&Me-","name":"SMILE -You&Me-"},{"url":"/闪耀吧Now","name":"闪耀吧Now"},{"url":"/是呢_白与黑","name":"是呢 白与黑"},{"url":"/Sister's_noise","name":"Sister's noise"},{"url":"/Special_\"ONE\"","name":"Special \"ONE\""},{"url":"/Stand_still","name":"Stand still"},{"url":"/完美心愿","name":"完美心愿"},{"url":"/Way_to_answer","name":"Way to answer"},{"url":"/于青岚之后","name":"于青岚之后"}],"subcategories":[{"name":"某科学的超电磁炮同人音乐","url":"/Category:某科学的超电磁炮同人音乐","pages":[{"url":"/木兰行(上条当麻先生)","name":"木兰行(上条当麻先生)"},{"url":"/唯我超电磁炮","name":"唯我超电磁炮"}],"subcategories":[]}]},{"name":"幽幻姐妹","url":"/Category:幽幻姐妹","pages":[{"url":"/幽幻姐妹","name":"幽幻姐妹"},{"url":"/北条彩铃","name":"北条彩铃"},{"url":"/牧上小牧","name":"牧上小牧"},{"url":"/真子(魔法禁书目录)","name":"真子(魔法禁书目录)"}],"subcategories":[],"article":{"page":"幽幻姐妹","url":"/幽幻姐妹"}},{"name":"孤独摇滚！音乐","url":"/Category:孤独摇滚！音乐","pages":[{"url":"/User:72Lee/Sandbox2","name":"User:72Lee/Sandbox2"},{"url":"/唱不出情歌","name":"唱不出情歌"},{"url":"/Distortion!!","name":"Distortion!!"},{"url":"/纷乱嘈杂","name":"纷乱嘈杂"},{"url":"/Flash_backer","name":"Flash backer"},{"url":"/感冒之歌","name":"感冒之歌"},{"url":"/孤独东京","name":"孤独东京"},{"url":"/滚动的岩石，晨光落在你身上","name":"滚动的岩石，晨光落在你身上"},{"url":"/吉他是朋友","name":"吉他是朋友"},{"url":"/吉他与孤独与蓝色星球","name":"吉他与孤独与蓝色星球"},{"url":"/鸡尾酒之歌","name":"鸡尾酒之歌"},{"url":"/绝不会忘记","name":"绝不会忘记"},{"url":"/来自壁橱的爱","name":"来自壁橱的爱"},{"url":"/秘密基地(结束乐队)","name":"秘密基地(结束乐队)"},{"url":"/那个乐队","name":"那个乐队"},{"url":"/青春与西方的天空","name":"青春与西方的天空"},{"url":"/青春症候群","name":"青春症候群"},{"url":"/若成为星座","name":"若成为星座"},{"url":"/双重黑历史孤独弹唱version","name":"双重黑历史孤独弹唱version"},{"url":"/向光(结束乐队)","name":"向光(结束乐队)"},{"url":"/小小海洋","name":"小小海洋"},{"url":"/幽灵唯我一人","name":"幽灵唯我一人"},{"url":"/有什么不好","name":"有什么不好"}],"subcategories":[]},{"name":"新世纪福音战士音乐","url":"/Category:新世纪福音战士音乐","pages":[{"url":"/Beautiful_World(宇多田光)","name":"Beautiful World(宇多田光)"},{"url":"/残酷天使的行动纲领","name":"残酷天使的行动纲领"},{"url":"/FLY_ME_TO_THE_MOON(EVA)","name":"FLY ME TO THE MOON(EVA)"},{"url":"/给我一双翅膀","name":"给我一双翅膀"},{"url":"/魂之轮回","name":"魂之轮回"},{"url":"/来吧，甜蜜的死亡","name":"来吧，甜蜜的死亡"},{"url":"/One_Last_Kiss","name":"One Last Kiss"},{"url":"/VOYAGER～没有日期的墓碑","name":"VOYAGER～没有日期的墓碑"},{"url":"/樱花纷飞","name":"樱花纷飞"}],"subcategories":[]},{"name":"少女终末旅行音乐","url":"/Category:少女终末旅行音乐","pages":[{"url":"/登山缆车","name":"登山缆车"},{"url":"/动起来、动起来","name":"动起来、动起来"},{"url":"/Endless_Journey","name":"Endless Journey"},{"url":"/More_One_Night","name":"More One Night"},{"url":"/雨滴之歌","name":"雨滴之歌"}],"subcategories":[]},{"name":"凉宫春日的性转换","url":"/Category:凉宫春日的性转换","pages":[{"url":"/古泉一姬","name":"古泉一姬"},{"url":"/国木田(凉宫春日的性转换)","name":"国木田(凉宫春日的性转换)"},{"url":"/虚子","name":"虚子"}],"subcategories":[],"article":{"page":"凉宫春日的性转换","url":"/index.php?title=凉宫春日的性转换&action=edit&redlink=1"}},{"name":"凉宫春日系列音乐","url":"/Category:凉宫春日系列音乐","pages":[{"url":"/超级好奇心","name":"超级好奇心"},{"url":"/窗边的预感","name":"窗边的预感"},{"url":"/风吹福到","name":"风吹福到"},{"url":"/God_knows...","name":"God knows..."},{"url":"/I'm_Freedom","name":"I'm Freedom"},{"url":"/就这样_JET_JUMPER","name":"就这样 JET JUMPER"},{"url":"/恋之实玖瑠传说","name":"恋之实玖瑠传说"},{"url":"/Lost_my_music","name":"Lost my music"},{"url":"/飘雪的未来","name":"飘雪的未来"},{"url":"/潜在的太阳的证明","name":"潜在的太阳的证明"},{"url":"/青春有什么不好","name":"青春有什么不好"},{"url":"/晴天好心情","name":"晴天好心情"},{"url":"/是冒险对吧对吧?","name":"是冒险对吧对吧?"},{"url":"/Super_Driver","name":"Super Driver"},{"url":"/停下吧！","name":"停下吧！"},{"url":"/温柔的忘却","name":"温柔的忘却"},{"url":"/我遗忘的东西","name":"我遗忘的东西"},{"url":"/Wonder_trip","name":"Wonder trip"},{"url":"/像是后记的东西","name":"像是后记的东西"},{"url":"/谢谢你，最喜欢","name":"谢谢你，最喜欢"},{"url":"/幸福就在日常中","name":"幸福就在日常中"},{"url":"/雪、无声、窗边。","name":"雪、无声、窗边。"},{"url":"/因为地球在转动","name":"因为地球在转动"},{"url":"/至今为止的概要","name":"至今为止的概要"}],"subcategories":[]},{"name":"轻音少女! Shuffle","url":"/Category:轻音少女!_Shuffle","pages":[{"url":"/清水枫","name":"清水枫"},{"url":"/轻音少女!_Shuffle","name":"轻音少女! Shuffle"},{"url":"/泽部真帆","name":"泽部真帆"},{"url":"/佐久间紫","name":"佐久间紫"}],"subcategories":[],"article":{"page":"轻音少女! Shuffle","url":"/轻音少女!_Shuffle"}},{"name":"轻音少女音乐","url":"/Category:轻音少女音乐","pages":[{"url":"/拜倒在吉太之下","name":"拜倒在吉太之下"},{"url":"/Cagayake!GIRLS","name":"Cagayake!GIRLS"},{"url":"/苍空的独白","name":"苍空的独白"},{"url":"/草莓芭菲吃得停不下来","name":"草莓芭菲吃得停不下来"},{"url":"/纯纯的心","name":"纯纯的心"},{"url":"/纯情Bomber!!","name":"纯情Bomber!!"},{"url":"/Come_with_Me!!","name":"Come with Me!!"},{"url":"/Cooly_Hotty_Tension_Hi!!","name":"Cooly Hotty Tension Hi!!"},{"url":"/Don't_say_\"lazy\"","name":"Don't say \"lazy\""},{"url":"/冬之日","name":"冬之日"},{"url":"/Drumming_Shining_My_Life","name":"Drumming Shining My Life"},{"url":"/放学后TEA_TIME(歌曲)","name":"放学后TEA TIME(歌曲)"},{"url":"/GENOM","name":"GENOM"},{"url":"/GO!_GO!_MANIAC","name":"GO! GO! MANIAC"},{"url":"/Genius...!?","name":"Genius...!?"},{"url":"/Girls_in_Wonderland","name":"Girls in Wonderland"},{"url":"/Girly_Storm_疾走_Stick","name":"Girly Storm 疾走 Stick"},{"url":"/光(轻音少女)","name":"光(轻音少女)"},{"url":"/龟兔赛跑","name":"龟兔赛跑"},{"url":"/Happy!?_Sorry!!","name":"Happy!? Sorry!!"},{"url":"/Heart_Goes_Boom!!","name":"Heart Goes Boom!!"},{"url":"/Hell_The_World","name":"Hell The World"},{"url":"/Hello_Little_Girl","name":"Hello Little Girl"},{"url":"/Honey_sweet_tea_time","name":"Honey sweet tea time"},{"url":"/欢欣雀跃New!_My_Way","name":"欢欣雀跃New! My Way"},{"url":"/Humming_Bird","name":"Humming Bird"},{"url":"/Joyful_Todays","name":"Joyful Todays"},{"url":"/Jump(轻音少女)","name":"Jump(轻音少女)"},{"url":"/咖喱后米饭","name":"咖喱后米饭"},{"url":"/Let's_Go(轻音少女)","name":"Let's Go(轻音少女)"},{"url":"/Listen!!","name":"Listen!!"},{"url":"/Love(轻音少女)","name":"Love(轻音少女)"},{"url":"/Lovely_Sister_LOVE","name":"Lovely Sister LOVE"},{"url":"/Maddy_Candy","name":"Maddy Candy"},{"url":"/毛笔_～圆珠笔～","name":"毛笔 ～圆珠笔～"},{"url":"/米饭是菜","name":"米饭是菜"},{"url":"/Midnight_Super_Star","name":"Midnight Super Star"},{"url":"/目标快乐百分百","name":"目标快乐百分百"},{"url":"/NO,_Thank_You!","name":"NO, Thank You!"},{"url":"/Oh_My_吉太!!","name":"Oh My 吉太!!"},{"url":"/Oui!爱的言语","name":"Oui!爱的言语"},{"url":"/Our_MAGIC","name":"Our MAGIC"},{"url":"/Over_the_Starlight","name":"Over the Starlight"},{"url":"/Prologue(轻音少女)","name":"Prologue(轻音少女)"},{"url":"/亲爱的琴键_键盘的魔法","name":"亲爱的琴键 键盘的魔法"},{"url":"/青春Vibration","name":"青春Vibration"},{"url":"/轻飘飘的时间","name":"轻飘飘的时间"},{"url":"/轻音少女/音乐列表","name":"轻音少女/音乐列表"},{"url":"/全部都是第一","name":"全部都是第一"},{"url":"/日记是最强音","name":"日记是最强音"},{"url":"/闪闪发光Days","name":"闪闪发光Days"},{"url":"/Shiny_GEMS","name":"Shiny GEMS"},{"url":"/Singing!","name":"Singing!"},{"url":"/Sunday_Siesta","name":"Sunday Siesta"},{"url":"/Sweet_Bitter_Beauty_Song","name":"Sweet Bitter Beauty Song"},{"url":"/同野马前行","name":"同野马前行"},{"url":"/U&I","name":"U&I"},{"url":"/Unmei_wa_Endless!","name":"Unmei wa Endless!"},{"url":"/Utauyo!!MIRACLE","name":"Utauyo!!MIRACLE"},{"url":"/我的爱是订书机","name":"我的爱是订书机"},{"url":"/我走我的道路","name":"我走我的道路"},{"url":"/五月雨20Love","name":"五月雨20Love"},{"url":"/夕阳天点菜","name":"夕阳天点菜"},{"url":"/向阳Living","name":"向阳Living"},{"url":"/相遇天使","name":"相遇天使"},{"url":"/心跳砂糖","name":"心跳砂糖"},{"url":"/幸福日和","name":"幸福日和"},{"url":"/野性的热情","name":"野性的热情"},{"url":"/樱丘女子高等学校校歌","name":"樱丘女子高等学校校歌"},{"url":"/雨降","name":"雨降"},{"url":"/早上好_明天见","name":"早上好 明天见"}],"subcategories":[]},{"name":"宫河家的空腹","url":"/Category:宫河家的空腹","pages":[{"url":"/宫河日向","name":"宫河日向"},{"url":"/宫河日影","name":"宫河日影"}],"subcategories":[{"name":"宫河家的空腹音乐","url":"/Category:宫河家的空腹音乐","pages":[{"url":"/MAKEGUMI","name":"MAKEGUMI"}],"subcategories":[]}]},{"name":"幸运星音乐","url":"/Category:幸运星音乐","pages":[{"url":"/不要认输","name":"不要认输"},{"url":"/CHA-LA_HEAD-CHA-LA","name":"CHA-LA HEAD-CHA-LA"},{"url":"/地上之星","name":"地上之星"},{"url":"/Gravity(幸运星)","name":"Gravity(幸运星)"},{"url":"/还给我！长筒袜","name":"还给我！长筒袜"},{"url":"/恋之实玖瑠传说","name":"恋之实玖瑠传说"},{"url":"/拿去吧！水手服","name":"拿去吧！水手服"},{"url":"/三十路岬","name":"三十路岬"},{"url":"/逃进·梦乡·Reset!","name":"逃进·梦乡·Reset!"},{"url":"/我遗忘的东西","name":"我遗忘的东西"},{"url":"/幸运星/角色歌","name":"幸运星/角色歌"},{"url":"/组曲「幸运星动画」","name":"组曲「幸运星动画」"}],"subcategories":[{"name":"宫河家的空腹音乐","url":"/Category:宫河家的空腹音乐","pages":[],"subcategories":[]}]},{"name":"中二病也要谈恋爱！音乐","url":"/Category:中二病也要谈恋爱！音乐","pages":[{"url":"/-Across_the_line-","name":"-Across the line-"},{"url":"/给你","name":"给你"},{"url":"/INSIDE_IDENTITY","name":"INSIDE IDENTITY"},{"url":"/JOURNEY(ZAQ)","name":"JOURNEY(ZAQ)"},{"url":"/觉醒Ragnarok_-暗黑启示录-","name":"觉醒Ragnarok -暗黑启示录-"},{"url":"/开始之种","name":"开始之种"},{"url":"/Please,Take_on_me","name":"Please,Take on me"},{"url":"/起舞于深渊的战栗狂欢节","name":"起舞于深渊的战栗狂欢节"},{"url":"/人大森_我叫要不","name":"人大森 我叫要不"},{"url":"/Secret_Survivor","name":"Secret Survivor"},{"url":"/Sparkling_Daydream","name":"Sparkling Daydream"},{"url":"/VOICE(ZAQ)","name":"VOICE(ZAQ)"},{"url":"/Van!shment_Th!s_World","name":"Van!shment Th!s World"},{"url":"/心的名字","name":"心的名字"},{"url":"/跃动于漆黑的弧浊霸王曲","name":"跃动于漆黑的弧浊霸王曲"},{"url":"/在你身边(ZAQ)","name":"在你身边(ZAQ)"}],"subcategories":[]},{"name":"玉子市场音乐","url":"/Category:玉子市场音乐","pages":[{"url":"/Call_me_Anne","name":"Call me Anne"},{"url":"/Call_me_Anne_Louder","name":"Call me Anne Louder"},{"url":"/点灯","name":"点灯"},{"url":"/Dramatic_Market_Ride","name":"Dramatic Market Ride"},{"url":"/二重奏Crescendo","name":"二重奏Crescendo"},{"url":"/Girlfriend(玉子市场)","name":"Girlfriend(玉子市场)"},{"url":"/今天和明天","name":"今天和明天"},{"url":"/今天也说不出口","name":"今天也说不出口"},{"url":"/KOI_NO_UTA","name":"KOI NO UTA"},{"url":"/哐当哐当嘎吱嘎吱","name":"哐当哐当嘎吱嘎吱"},{"url":"/恋歌(北白川玉子)","name":"恋歌(北白川玉子)"},{"url":"/你的魔法","name":"你的魔法"},{"url":"/年糕Affection！","name":"年糕Affection！"},{"url":"/Principle","name":"Principle"},{"url":"/Qum_Daiwtiigyam","name":"Qum Daiwtiigyam"},{"url":"/睡姿","name":"睡姿"},{"url":"/太阳和鼓","name":"太阳和鼓"},{"url":"/太阳与鼓与会说话的鸟","name":"太阳与鼓与会说话的鸟"},{"url":"/一定，永远，请多关照。","name":"一定，永远，请多关照。"},{"url":"/致豆大","name":"致豆大"}],"subcategories":[]}]}